django_environ_var/__init__.py
django_environ_var/env.py
django_environ_var-0.1.dist-info/METADATA
django_environ_var-0.1.dist-info/WHEEL
django_environ_var-0.1.dist-info/top_level.txt
django_environ_var-0.1.dist-info/RECORD
